nbh_main/__init__.py
nbh_main/apps.py
nbh_main/loggers.py
nbh_main/settings.py
nbh_main/sitesettings.py
nbh_main/urls.py
nbh_main/views.py
nbh_main/wsgi.py
nbh_main/management/__init__.py
nbh_main/management/commands/__init__.py
nbh_main/management/commands/build_images.py
nbh_main/management/commands/group_list.py
nbh_main/management/commands/mass_register.py
nbh_main/management/commands/pull_students.py
nbh_main/management/commands/shell_sitesettings.py
nbh_main/management/commands/user_list.py
nbhosting/__init__.py
nbhosting/matching.py
nbhosting/utils.py
nbhosting/version.py
nbhosting/courses/__init__.py
nbhosting/courses/admin.py
nbhosting/courses/apps.py
nbhosting/courses/forms.py
nbhosting/courses/model_build.py
nbhosting/courses/model_course.py
nbhosting/courses/model_dropped.py
nbhosting/courses/model_mapping.py
nbhosting/courses/model_track.py
nbhosting/courses/tests.py
nbhosting/courses/views_auditor.py
nbhosting/courses/views_staff.py
nbhosting/courses/views_teacher.py
nbhosting/courses/management/__init__.py
nbhosting/courses/management/commands/__init__.py
nbhosting/courses/management/commands/course_auto_pull.py
nbhosting/courses/management/commands/course_build_image.py
nbhosting/courses/management/commands/course_create.py
nbhosting/courses/management/commands/course_delete.py
nbhosting/courses/management/commands/course_group.py
nbhosting/courses/management/commands/course_image_details.py
nbhosting/courses/management/commands/course_list.py
nbhosting/courses/management/commands/course_pull.py
nbhosting/courses/management/commands/course_rename.py
nbhosting/courses/management/commands/course_run_build.py
nbhosting/courses/management/commands/course_tracks.py
nbhosting/courses/migrations/0001_initial.py
nbhosting/courses/migrations/0002_registered_groups.py
nbhosting/courses/migrations/0003_coursedir_archived.py
nbhosting/courses/migrations/0004_coursedir_autobuild.py
nbhosting/courses/migrations/0005_alter_coursedir_id.py
nbhosting-0.57.1.dist-info/METADATA
nbhosting-0.57.1.dist-info/WHEEL
nbhosting-0.57.1.dist-info/top_level.txt
nbhosting-0.57.1.dist-info/RECORD
