Metadata-Version: 2.1
Name: nbhosting
Version: 0.57.1
Summary: An infrastructure for hosting notebooks behind an open-edX MOOC platform, or for registered students like in a classroom
Home-page: https://github.com/parmentelat/nbhosting
Author: Thierry Parmentelat
Author-email: thierry.parmentelat@inria.fr
License: See LICENSE
Classifier: Development Status :: 3 - Alpha
Classifier: Programming Language :: Python :: 3.8
Classifier: Programming Language :: Python :: 3.9
Requires-Dist: pip
Requires-Dist: setuptools
Requires-Dist: wheel
Requires-Dist: django
Requires-Dist: django-extensions
Requires-Dist: jsonpickle
Requires-Dist: nbformat
Requires-Dist: jupytext
Requires-Dist: aiohttp
Requires-Dist: podman
Requires-Dist: rich
Requires-Dist: redis
Requires-Dist: nbstripout
Requires-Dist: pandas
